{
  "bulbasaur": {"x": 230, "y": 170, "bg": "grass.png"}, "ivysaur": {"x": 200, "y": 150, "bg": "grass.png"},
  "venusaur": {"x": 200, "y": 110, "bg": "grass.png"}, "charmander": {"x": 230, "y": 110, "bg": "fire.png"},
  "charmeleon": {"x": 230, "y": 90, "bg": "fire.png"}, "charizard": {"x": 200, "y": 0, "bg": "fire.png"},
  "squirtle": {"x": 230, "y": 110, "bg": "water.png"}, "wartortle": {"x": 200, "y": 90, "bg": "water.png"},
  "blastoise": {"x": 200, "y": 75, "bg": "water.png"}, "caterpie": {"x": 220, "y": 180, "bg": "bug.png"},
  "metapod": {"x": 220, "y": 180, "bg": "bug.png"}, "butterfree": {"x": 200, "y": 110, "bg": "flying.png"},
  "weedle": {"x": 220, "y": 180, "bg": "bug.png"}, "kakuna": {"x": 220, "y": 180, "bg": "bug.png"},
  "beedrill": {"x": 170, "y": 50, "bg": "bug.png"}, "pidgey": {"x": 200, "y": 110, "bg": "normal.jpg"},
  "pidgeotto": {"x": 200, "y": 0, "bg": "flying.jpg"}, "pidgeot": {"x": 200, "y": 80, "bg": "normal.jpg"},
  "rattata": {"x": 200, "y": 110, "bg": "normal.jpeg"}, "raticate": {"x": 200, "y": 110, "bg": "normal.jpeg"},
  "spearow": {"x": 240, "y": 130, "bg": "normal.jpg"}, "fearow": {"x": 200, "y": 0, "bg": "flying.jpg"},
  "ekans": {"x": 200, "y": 110, "bg": "poison.png"}, "arbok": {"x": 180, "y": 30, "bg": "poison.png"},
  "pikachu": {"x": 220, "y": 150, "bg": "grass.png"}, "raichu": {"x": 180, "y": 90, "bg": "grass.png"},
  "clefairy": {"x": 200, "y": 110, "bg": "normal.jpeg"}, "clefable": {"x": 200, "y": 110, "bg": "normal.jpeg"},
  "vulpix": {"x": 200, "y": 140, "bg": "grass.png"}, "ninetales": {"x": 200, "y": 110, "bg": "grass.png"},
  "jigglypuff": {"x": 200, "y": 110, "bg": "normal.jpeg"}, "wigglytuff": {"x": 200, "y": 110, "bg": "normal.jpeg"},
  "zubat": {"x": 200, "y": 110, "bg": "flying.jpg"}, "golbat": {"x": 200, "y": 110, "bg": "flying.jpg"},
  "oddish": {"x": 200, "y": 110, "bg": "grass.png"}, "gloom": {"x": 200, "y": 110, "bg": "grass.png"},
  "vileplume": {"x": 200, "y": 110, "bg": "grass.png"}, "paras": {"x": 200, "y": 110, "bg": "bug.png"},
  "parasect": {"x": 200, "y": 110, "bg": "bug.png"}, "venonat": {"x": 200, "y": 110, "bg": "bug.png"},
  "venomoth": {"x": 200, "y": 110, "bg": "bug.png"}, "diglett": {"x": 200, "y": 110, "bg": "ground.png"},
  "dugtrio": {"x": 200, "y": 110, "bg": "ground.png"}, "meowth": {"x": 200, "y": 110, "bg": "normal.jpeg"},
  "persian": {"x": 200, "y": 110, "bg": "normal.jpeg"}, "psyduck": {"x": 200, "y": 110, "bg": "water.png"},
  "golduck": {"x": 200, "y": 110, "bg": "water.png"}, "mankey": {"x": 200, "y": 110, "bg": "fighting.jpeg"},
  "primeape": {"x": 200, "y": 110, "bg": "fighting.jpeg"}, "growlithe": {"x": 200, "y": 110, "bg": "fire.png"},
  "arcanine": {"x": 200, "y": 110, "bg": "fire.png"}, "poliwag": {"x": 200, "y": 110, "bg": "water.png"},
  "poliwhirl": {"x": 200, "y": 110, "bg": "water.png"}, "poliwrath": {"x": 200, "y": 110, "bg": "water.png"},
  "abra": {"x": 200, "y": 110, "bg": "normal.jpeg"}, "kadabra": {"x": 200, "y": 110, "bg": "normal.jpeg"},
  "alakazam": {"x": 200, "y": 110, "bg": "normal.jpeg"}, "machop": {"x": 200, "y": 110, "bg": "fighting.jpeg"},
  "machoke": {"x": 200, "y": 110, "bg": "fighting.jpeg"}, "machamp": {"x": 200, "y": 110, "bg": "fighting.jpeg"},
  "bellsprout": {"x": 200, "y": 110, "bg": "grass.png"}, "weepinbell": {"x": 200, "y": 110, "bg": "grass.png"},
  "victreebel": {"x": 200, "y": 110, "bg": "grass.png"}, "tentacool": {"x": 200, "y": 110, "bg": "water.png"},
  "tentacruel": {"x": 200, "y": 110, "bg": "water.png"}, "slowpoke": {"x": 200, "y": 110, "bg": "water.png"},
  "slowbro": {"x": 200, "y": 110, "bg": "water.png"}, "seel": {"x": 200, "y": 110, "bg": "water.png"},
  "dewgong": {"x": 200, "y": 110, "bg": "ice.png"}, "shellder": {"x": 200, "y": 110, "bg": "water.png"},
  "cloyster": {"x": 200, "y": 110, "bg": "water.png"}, "gastly": {"x": 200, "y": 110, "bg": "ghost.png"},
  "haunter": {"x": 200, "y": 110, "bg": "ghost.png"}, "gengar": {"x": 200, "y": 110, "bg": "ghost.png"},
  "onix": {"x": 200, "y": 110, "bg": "rock.png"}, "drowzee": {"x": 200, "y": 110, "bg": "normal.jpeg"},
  "hypno": {"x": 200, "y": 110, "bg": "normal.jpeg"}, "krabby": {"x": 200, "y": 110, "bg": "water.png"},
  "kingler": {"x": 200, "y": 110, "bg": "water.png"}, "horsea": {"x": 200, "y": 110, "bg": "water.png"},
  "seadra": {"x": 200, "y": 110, "bg": "water.png"}, "goldeen": {"x": 200, "y": 110, "bg": "water.png"},
  "seaking": {"x": 200, "y": 110, "bg": "water.png"}, "staryu": {"x": 200, "y": 110, "bg": "water.png"},
  "starmie": {"x": 200, "y": 110, "bg": "water.png"}, "mr-mime": {"x": 200, "y": 110, "bg": "normal.jpeg"},
  "scyther": {"x": 200, "y": 110, "bg": "bug.png"}, "jynx": {"x": 200, "y": 110, "bg": "ice.png"},
  "electabuzz": {"x": 200, "y": 110, "bg": "electric.png"}, "magby": {"x": 200, "y": 110, "bg": "fire.png"},
  "magnemite": {"x": 200, "y": 110, "bg": "steel.png"}, "magneton": {"x": 200, "y": 110, "bg": "steel.png"},
  "farfetchd": {"x": 200, "y": 110, "bg": "flying.jpg"}, "doduo": {"x": 200, "y": 110, "bg": "flying.jpg"},
  "dodrio": {"x": 200, "y": 110, "bg": "flying.jpg"}, "grimer": {"x": 200, "y": 110, "bg": "poison.png"},
  "muk": {"x": 200, "y": 110, "bg": "poison.png"}, "voltorb": {"x": 200, "y": 110, "bg": "electric.png"},
  "electrode": {"x": 200, "y": 110, "bg": "electric.png"}, "exeggcute": {"x": 200, "y": 110, "bg": "grass.png"},
  "exeggutor": {"x": 200, "y": 110, "bg": "grass.png"}, "cubone": {"x": 200, "y": 110, "bg": "ground.png"},
  "marowak": {"x": 200, "y": 110, "bg": "ground.png"}, "hitmonlee": {"x": 200, "y": 110, "bg": "fighting.jpeg"},
  "hitmonchan": {"x": 200, "y": 110, "bg": "fighting.jpeg"}, "lickitung": {"x": 200, "y": 110, "bg": "normal.jpeg"},
  "koffing": {"x": 200, "y": 110, "bg": "poison.png"}, "weezing": {"x": 200, "y": 110, "bg": "poison.png"},
  "rhyhorn": {"x": 200, "y": 110, "bg": "ground.png"}, "rhydon": {"x": 200, "y": 110, "bg": "ground.png"},
  "chansey": {"x": 200, "y": 110, "bg": "normal.jpeg"}, "kangaskhan": {"x": 200, "y": 110, "bg": "normal.jpeg"},
  "tangela": {"x": 200, "y": 110, "bg": "grass.png"}, "lapras": {"x": 200, "y": 110, "bg": "water.png"},
  "ditto": {"x": 200, "y": 110, "bg": "normal.jpeg"}, "eevee": {"x": 200, "y": 110, "bg": "normal.jpeg"},
  "vaporeon": {"x": 200, "y": 110, "bg": "water.png"}, "jolteon": {"x": 200, "y": 110, "bg": "electric.png"},
  "flareon": {"x": 200, "y": 110, "bg": "fire.png"}, "porygon": {"x": 200, "y": 110, "bg": "normal.jpeg"},
  "omanyte": {"x": 200, "y": 110, "bg": "water.png"}, "omastar": {"x": 200, "y": 110, "bg": "water.png"},
  "kabuto": {"x": 200, "y": 110, "bg": "water.png"}, "kabutops": {"x": 200, "y": 110, "bg": "water.png"},
  "aerodactyl": {"x": 200, "y": 110, "bg": "rock.png"}, "snorlax": {"x": 200, "y": 110, "bg": "normal.jpeg"},
  "articuno": {"x": 200, "y": 110, "bg": "ice.png"}, "zapdos": {"x": 200, "y": 110, "bg": "electric.png"},
  "moltres": {"x": 200, "y": 110, "bg": "fire.png"}, "dratini": {"x": 200, "y": 110, "bg": "dragon.jpeg"},
  "dragonair": {"x": 200, "y": 110, "bg": "dragon.jpeg"}, "dragonite": {"x": 200, "y": 110, "bg": "dragon.jpeg"},
  "mewtwo": {"x": 200, "y": 110, "bg": "normal.jpeg"}, "mew": {"x": 200, "y": 110, "bg": "normal.jpeg"}
}
